AUTHORS
LICENSE
MANIFEST.in
README.rst
requirements.txt
setup.py
version.py
alignak_module_EXAMPLE.egg-info/PKG-INFO
alignak_module_EXAMPLE.egg-info/SOURCES.txt
alignak_module_EXAMPLE.egg-info/dependency_links.txt
alignak_module_EXAMPLE.egg-info/not-zip-safe
alignak_module_EXAMPLE.egg-info/top_level.txt
alignak_module_example/__init__.py
alignak_module_example/__init__.pyc
alignak_module_example/example.py
alignak_module_example/example.pyc
alignak_module_example/etc/__init__.py
alignak_module_example/etc/arbiter/modules/mod-example.cfg
test/test_module.py